MANIFEST.in
README.rst
pygments.rst
setup.py
pygments_ibm_cobol_lexer/__init__.py
pygments_ibm_cobol_lexer.egg-info/PKG-INFO
pygments_ibm_cobol_lexer.egg-info/SOURCES.txt
pygments_ibm_cobol_lexer.egg-info/dependency_links.txt
pygments_ibm_cobol_lexer.egg-info/entry_points.txt
pygments_ibm_cobol_lexer.egg-info/requires.txt
pygments_ibm_cobol_lexer.egg-info/top_level.txt
pygments_tests/COB001.cp1147.cbl
pygments_tests/COB001.html
pygments_tests/HORREUR.ascii.cbl
pygments_tests/HORREUR.cp1140.cbl
pygments_tests/HORREUR.html
pygments_tests/highlight.py
pygments_tests/highlight.py~
pygments_tests/ibmcob.css