Metadata-Version: 1.0
Name: pygments-ibm-cobol-lexer
Version: 1.2
Summary: Cobol IBM Mainframe syntax lexer for Pygments
Home-page: http://www.datim.fr
Author: Denis Wallerich
Author-email: denis.wallerich@datim.fr
License: BSD
Platform: UNKNOWN
